shootout/methods/pipeplines.py
shootout/methods/plotters.py
shootout/methods/post_processors.py
shootout/methods/runners.py
shootout/tests/test_plotters.py
shootout/tests/test_post_processors.py
shootout/tests/test_runners.py
shootout_opt-0.2.3.dist-info/LICENSE
shootout_opt-0.2.3.dist-info/METADATA
shootout_opt-0.2.3.dist-info/WHEEL
shootout_opt-0.2.3.dist-info/top_level.txt
shootout_opt-0.2.3.dist-info/RECORD
