Metadata-Version: 2.1
Name: shootout-opt
Version: 0.2.3
Summary: Run algorithms, store and compare their outputs
Author-email: "Jeremy E. Cohen" <jeremy.cohen@cnrs.fr>
License: MIT License
Project-URL: Homepage, https://cohenjer.github.io/shootout
Keywords: numerical optimisation,visualisation,python
Requires-Python: >=3.9
License-File: LICENSE
Requires-Dist: numpy (>=1.23)
Requires-Dist: plotly (>=5.8.2)
Requires-Dist: kaleido (>=0.2.1)
Requires-Dist: matplotlib (>=3.5.3)
Requires-Dist: pandas (>=1.4.2)
Provides-Extra: dev
Requires-Dist: pytest ; extra == 'dev'
